{
  "project_info": {
    "project_number": "759344600312",
    "firebase_url": "https://startauth-default-rtdb.firebaseio.com",
    "project_id": "startauth",
    "storage_bucket": "startauth.appspot.com"
  },
  "client": [
    {
      "client_info": {
        "mobilesdk_app_id": "1:759344600312:android:1fd889b21547de3900570d",
        "android_client_info": {
          "package_name": "com.example.start"
        }
      },
      "oauth_client": [
        {
          "client_id": "759344600312-6fc9d1qtra4c7ebspa967us627t7av79.apps.googleusercontent.com",
          "client_type": 3
        }
      ],
      "api_key": [
        {
          "current_key": "AIzaSyA5Pe17wn5bM4B3nzbrY5YBFLUubDUNoKk"
        }
      ],
      "services": {
        "appinvite_service": {
          "other_platform_oauth_client": [
            {
              "client_id": "759344600312-6fc9d1qtra4c7ebspa967us627t7av79.apps.googleusercontent.com",
              "client_type": 3
            }
          ]
        }
      }
    }
  ],
  "configuration_version": "1"
}